adabelief_tf/AdaBelief_tf.py
adabelief_tf/__init__.py
adabelief_tf-0.2.1.dist-info/LICENSE.txt
adabelief_tf-0.2.1.dist-info/METADATA
adabelief_tf-0.2.1.dist-info/WHEEL
adabelief_tf-0.2.1.dist-info/top_level.txt
adabelief_tf-0.2.1.dist-info/RECORD
